rodi/__about__.py
rodi/__init__.py
rodi/py.typed
rodi-2.0.8.dist-info/METADATA
rodi-2.0.8.dist-info/WHEEL
rodi-2.0.8.dist-info/licenses/LICENSE
rodi-2.0.8.dist-info/RECORD
